PyCRC/__init__.py
PyCRC/bcc.py
PyCRC/crc.py
PyCRC/lrc.py
test/__init__.py
test/aa.py
PyCRC_Hex-1.1.0.dist-info/LICENSE
PyCRC_Hex-1.1.0.dist-info/METADATA
PyCRC_Hex-1.1.0.dist-info/WHEEL
PyCRC_Hex-1.1.0.dist-info/top_level.txt
PyCRC_Hex-1.1.0.dist-info/RECORD
