Metadata-Version: 2.1
Name: PyCRC-Hex
Version: 1.1.0
Summary: Python Cyclic Redundancy Check,LRC,BCC
Home-page: https://github.com/1484076353/PyCRC
Author: ChenJun0177112278@163.com
Author-email: ChenJun0177112278@163.com
License: MIT
Platform: UNKNOWN
